ab_sdk_account_test/__init__.py
ab_sdk_account_test/account_test.py
ab_sdk_account_test/invoice_test.py
ab_sdk_account_test/order_test.py
ab_sdk_account_test/payment_test.py
ab_sdk_account_test/purchase_order_test.py
ab_sdk_account_test/setting_test.py
ab_sdk_account_test/common/__init__.py
ab_sdk_account_test/common/common_data.py
ab_sdk_account_test/tmp/__init__.py
ab_sdk_account_test/tmp/response_to_obj.py
ab_sdk_account_test-1.0.1.dist-info/LICENSE.txt
ab_sdk_account_test-1.0.1.dist-info/METADATA
ab_sdk_account_test-1.0.1.dist-info/WHEEL
ab_sdk_account_test-1.0.1.dist-info/top_level.txt
ab_sdk_account_test-1.0.1.dist-info/RECORD
